{
  "Id": "e0a628f0-67ef-4bf0-8936-9a92a54fb869",
  "Name": "VisitDailyAction",
  "OriginalName": "VisitDailyAction",
  "NamePlural": "VisitDailyActions",
  "DatabaseTableName": "VisitDailyActions",
  "Namespace": "VisitDailyActions",
  "BaseClass": "FullAuditedAggregateRoot",
  "MenuIcon": "file-alt",
  "PrimaryKeyType": "Guid",
  "IsMultiTenant": false,
  "CheckConcurrency": true,
  "ShouldCreateUserInterface": true,
  "ShouldCreateBackend": true,
  "ShouldExportExcel": true,
  "ShouldAddMigration": true,
  "ShouldUpdateDatabase": true,
  "CreateTests": true,
  "Properties": [
    {
      "Id": "34b8a5c3-528e-4768-8eca-7a81fdcf48d5",
      "Name": "VisitDailyDate",
      "Type": "DateTime",
      "EnumType": "",
      "EnumNamespace": "",
      "EnumAngularImport": "shared/enums",
      "EnumFilePath": null,
      "DefaultValue": null,
      "IsNullable": false,
      "IsRequired": false,
      "IsTextArea": false,
      "MinLength": null,
      "MaxLength": null,
      "SortOrder": 0,
      "SortType": 0,
      "Regex": "",
      "EmailValidation": false,
      "EnumValues": null,
      "IsSelected": true,
      "OrdinalIndex": 0
    },
    {
      "Id": "01bc1b92-e689-42f7-94ca-cd504703d3ac",
      "Name": "VisitDaily1",
      "Type": "decimal",
      "EnumType": "",
      "EnumNamespace": "",
      "EnumAngularImport": "shared/enums",
      "EnumFilePath": null,
      "DefaultValue": null,
      "IsNullable": false,
      "IsRequired": false,
      "IsTextArea": false,
      "MinLength": null,
      "MaxLength": null,
      "SortOrder": 0,
      "SortType": 0,
      "Regex": "",
      "EmailValidation": false,
      "EnumValues": null,
      "IsSelected": true,
      "OrdinalIndex": 0
    },
    {
      "Id": "d87824c0-27f7-48f0-acb9-813ba9736b07",
      "Name": "VisitDaily2",
      "Type": "decimal",
      "EnumType": "",
      "EnumNamespace": "",
      "EnumAngularImport": "shared/enums",
      "EnumFilePath": null,
      "DefaultValue": null,
      "IsNullable": false,
      "IsRequired": false,
      "IsTextArea": false,
      "MinLength": null,
      "MaxLength": null,
      "SortOrder": 0,
      "SortType": 0,
      "Regex": "",
      "EmailValidation": false,
      "EnumValues": null,
      "IsSelected": true,
      "OrdinalIndex": 0
    },
    {
      "Id": "4464d625-ef5d-4fea-9f8c-ad1048845bb6",
      "Name": "VisitDaily3",
      "Type": "decimal",
      "EnumType": "",
      "EnumNamespace": "",
      "EnumAngularImport": "shared/enums",
      "EnumFilePath": null,
      "DefaultValue": null,
      "IsNullable": false,
      "IsRequired": false,
      "IsTextArea": false,
      "MinLength": null,
      "MaxLength": null,
      "SortOrder": 0,
      "SortType": 0,
      "Regex": "",
      "EmailValidation": false,
      "EnumValues": null,
      "IsSelected": true,
      "OrdinalIndex": 0
    },
    {
      "Id": "1e4be345-7adc-4259-8acb-1658cdf9aa90",
      "Name": "VisitDaily4",
      "Type": "decimal",
      "EnumType": "",
      "EnumNamespace": "",
      "EnumAngularImport": "shared/enums",
      "EnumFilePath": null,
      "DefaultValue": null,
      "IsNullable": false,
      "IsRequired": false,
      "IsTextArea": false,
      "MinLength": null,
      "MaxLength": null,
      "SortOrder": 0,
      "SortType": 0,
      "Regex": "",
      "EmailValidation": false,
      "EnumValues": null,
      "IsSelected": true,
      "OrdinalIndex": 0
    },
    {
      "Id": "be088aac-069b-4737-88f8-c27d583ebf23",
      "Name": "VisitDaily5",
      "Type": "decimal",
      "EnumType": "",
      "EnumNamespace": "",
      "EnumAngularImport": "shared/enums",
      "EnumFilePath": null,
      "DefaultValue": null,
      "IsNullable": false,
      "IsRequired": false,
      "IsTextArea": false,
      "MinLength": null,
      "MaxLength": null,
      "SortOrder": 0,
      "SortType": 0,
      "Regex": "",
      "EmailValidation": false,
      "EnumValues": null,
      "IsSelected": true,
      "OrdinalIndex": 0
    },
    {
      "Id": "9085a7e6-ff49-4bef-b493-439d3ebe47a2",
      "Name": "VisitDaily6",
      "Type": "decimal",
      "EnumType": "",
      "EnumNamespace": "",
      "EnumAngularImport": "shared/enums",
      "EnumFilePath": null,
      "DefaultValue": null,
      "IsNullable": false,
      "IsRequired": false,
      "IsTextArea": false,
      "MinLength": null,
      "MaxLength": null,
      "SortOrder": 0,
      "SortType": 0,
      "Regex": "",
      "EmailValidation": false,
      "EnumValues": null,
      "IsSelected": true,
      "OrdinalIndex": 0
    },
    {
      "Id": "d2a6a2c2-cc8c-4ff2-9324-f9b76ef3306f",
      "Name": "VisitDaily7",
      "Type": "decimal",
      "EnumType": "",
      "EnumNamespace": "",
      "EnumAngularImport": "shared/enums",
      "EnumFilePath": null,
      "DefaultValue": null,
      "IsNullable": false,
      "IsRequired": false,
      "IsTextArea": false,
      "MinLength": null,
      "MaxLength": null,
      "SortOrder": 0,
      "SortType": 0,
      "Regex": "",
      "EmailValidation": false,
      "EnumValues": null,
      "IsSelected": true,
      "OrdinalIndex": 0
    },
    {
      "Id": "652870b6-7c7c-4a53-aba8-03189e79e9cd",
      "Name": "VisitDaily8",
      "Type": "decimal",
      "EnumType": "",
      "EnumNamespace": "",
      "EnumAngularImport": "shared/enums",
      "EnumFilePath": null,
      "DefaultValue": null,
      "IsNullable": false,
      "IsRequired": false,
      "IsTextArea": false,
      "MinLength": null,
      "MaxLength": null,
      "SortOrder": 0,
      "SortType": 0,
      "Regex": "",
      "EmailValidation": false,
      "EnumValues": null,
      "IsSelected": true,
      "OrdinalIndex": 0
    },
    {
      "Id": "bb910b03-c8c9-45ef-820d-1017a8716443",
      "Name": "VisitDaily9",
      "Type": "decimal",
      "EnumType": "",
      "EnumNamespace": "",
      "EnumAngularImport": "shared/enums",
      "EnumFilePath": null,
      "DefaultValue": null,
      "IsNullable": false,
      "IsRequired": false,
      "IsTextArea": false,
      "MinLength": null,
      "MaxLength": null,
      "SortOrder": 0,
      "SortType": 0,
      "Regex": "",
      "EmailValidation": false,
      "EnumValues": null,
      "IsSelected": true,
      "OrdinalIndex": 0
    },
    {
      "Id": "d2f5050a-2320-4ff3-8073-357324b89455",
      "Name": "VisitDaily10",
      "Type": "decimal",
      "EnumType": "",
      "EnumNamespace": "",
      "EnumAngularImport": "shared/enums",
      "EnumFilePath": null,
      "DefaultValue": null,
      "IsNullable": false,
      "IsRequired": false,
      "IsTextArea": false,
      "MinLength": null,
      "MaxLength": null,
      "SortOrder": 0,
      "SortType": 0,
      "Regex": "",
      "EmailValidation": false,
      "EnumValues": null,
      "IsSelected": true,
      "OrdinalIndex": 0
    },
    {
      "Id": "27c37a00-8c12-4f4a-b5c9-626a3cc8ebdc",
      "Name": "VisitDaily11",
      "Type": "decimal",
      "EnumType": "",
      "EnumNamespace": "",
      "EnumAngularImport": "shared/enums",
      "EnumFilePath": null,
      "DefaultValue": null,
      "IsNullable": false,
      "IsRequired": false,
      "IsTextArea": false,
      "MinLength": null,
      "MaxLength": null,
      "SortOrder": 0,
      "SortType": 0,
      "Regex": "",
      "EmailValidation": false,
      "EnumValues": null,
      "IsSelected": true,
      "OrdinalIndex": 0
    },
    {
      "Id": "ca6f1619-03a1-4ab4-8246-146164ac5da6",
      "Name": "VisitDaily12",
      "Type": "decimal",
      "EnumType": "",
      "EnumNamespace": "",
      "EnumAngularImport": "shared/enums",
      "EnumFilePath": null,
      "DefaultValue": null,
      "IsNullable": false,
      "IsRequired": false,
      "IsTextArea": false,
      "MinLength": null,
      "MaxLength": null,
      "SortOrder": 0,
      "SortType": 0,
      "Regex": "",
      "EmailValidation": false,
      "EnumValues": null,
      "IsSelected": true,
      "OrdinalIndex": 0
    },
    {
      "Id": "2022b666-27eb-4ebd-9e6b-9b4988706e94",
      "Name": "VisitDaily13",
      "Type": "decimal",
      "EnumType": "",
      "EnumNamespace": "",
      "EnumAngularImport": "shared/enums",
      "EnumFilePath": null,
      "DefaultValue": null,
      "IsNullable": false,
      "IsRequired": false,
      "IsTextArea": false,
      "MinLength": null,
      "MaxLength": null,
      "SortOrder": 0,
      "SortType": 0,
      "Regex": "",
      "EmailValidation": false,
      "EnumValues": null,
      "IsSelected": true,
      "OrdinalIndex": 0
    },
    {
      "Id": "639b3886-1d05-4d38-979b-8d9af0a386f2",
      "Name": "VisitDaily14",
      "Type": "decimal",
      "EnumType": "",
      "EnumNamespace": "",
      "EnumAngularImport": "shared/enums",
      "EnumFilePath": null,
      "DefaultValue": null,
      "IsNullable": false,
      "IsRequired": false,
      "IsTextArea": false,
      "MinLength": null,
      "MaxLength": null,
      "SortOrder": 0,
      "SortType": 0,
      "Regex": "",
      "EmailValidation": false,
      "EnumValues": null,
      "IsSelected": true,
      "OrdinalIndex": 0
    },
    {
      "Id": "1c738aa9-7028-4658-9484-be293df78005",
      "Name": "VisitDaily15",
      "Type": "decimal",
      "EnumType": "",
      "EnumNamespace": "",
      "EnumAngularImport": "shared/enums",
      "EnumFilePath": null,
      "DefaultValue": null,
      "IsNullable": false,
      "IsRequired": false,
      "IsTextArea": false,
      "MinLength": null,
      "MaxLength": null,
      "SortOrder": 0,
      "SortType": 0,
      "Regex": "",
      "EmailValidation": false,
      "EnumValues": null,
      "IsSelected": true,
      "OrdinalIndex": 0
    },
    {
      "Id": "80e0e353-f902-4bfb-85a5-51f42bbceb63",
      "Name": "VisitDailyCloseDate",
      "Type": "DateTime",
      "EnumType": "",
      "EnumNamespace": "",
      "EnumAngularImport": "shared/enums",
      "EnumFilePath": null,
      "DefaultValue": null,
      "IsNullable": false,
      "IsRequired": false,
      "IsTextArea": false,
      "MinLength": null,
      "MaxLength": null,
      "SortOrder": 0,
      "SortType": 0,
      "Regex": "",
      "EmailValidation": false,
      "EnumValues": null,
      "IsSelected": true,
      "OrdinalIndex": 0
    },
    {
      "Id": "6766a710-6242-49e8-b2a3-8b1b593061b8",
      "Name": "VisitDailyNote",
      "Type": "string",
      "EnumType": "",
      "EnumNamespace": "",
      "EnumAngularImport": "shared/enums",
      "EnumFilePath": null,
      "DefaultValue": null,
      "IsNullable": false,
      "IsRequired": false,
      "IsTextArea": false,
      "MinLength": null,
      "MaxLength": null,
      "SortOrder": 0,
      "SortType": 0,
      "Regex": "",
      "EmailValidation": false,
      "EnumValues": null,
      "IsSelected": true,
      "OrdinalIndex": 0
    }
  ],
  "NavigationProperties": [
    {
      "EntityNameWithDuplicationNumber": "IdentityUser",
      "EntitySetNameWithDuplicationNumber": "Users",
      "ReferencePropertyName": "IdentityUser",
      "UiPickType": "Dropdown",
      "IsRequired": false,
      "Name": "IdentityUserId",
      "DisplayProperty": "UserName",
      "Namespace": "Volo.Abp.Identity",
      "EntityName": "IdentityUser",
      "EntitySetName": "Users",
      "DtoNamespace": "Volo.Abp.Identity",
      "DtoEntityName": "IdentityUserDto",
      "Type": "Guid"
    }
  ],
  "NavigationConnections": [],
  "PhysicalFileName": "VisitDailyAction.json"
}